{"stock_code":"044180","name":"국제디와이","market":"KOSDAQ","sector":null,"years":[{"bsns_year":2015,"fs_div":"CFS","reprt_code":"11011","revenue":30009586865.0,"op_income":1439399049.0,"net_income":614557173.0,"total_assets":38509704339.0,"total_liab":21453690972.0,"total_equity":17056013367.0,"per":54.3391,"pbr":1.9579,"roe":0.036032,"roic":0.037378,"ev_ebit":23.200291,"op_margin":0.047965,"gp_a":0.139004},{"bsns_year":2016,"fs_div":"CFS","reprt_code":"11011","revenue":35750504470.0,"op_income":1566518444.0,"net_income":19499007.0,"total_assets":59541798552.0,"total_liab":20284261461.0,"total_equity":39257537091.0,"per":2369.6065,"pbr":1.177,"roe":0.000497,"roic":0.02631,"ev_ebit":29.495327,"op_margin":0.043818,"gp_a":0.103736},{"bsns_year":2017,"fs_div":"CFS","reprt_code":"11011","revenue":22401619346.0,"op_income":-10282184255.0,"net_income":-16710269605.0,"total_assets":98824539961.0,"total_liab":58046567256.0,"total_equity":40777972705.0,"per":null,"pbr":1.4828,"roe":-0.409787,"roic":-0.104045,"ev_ebit":null,"op_margin":-0.458993,"gp_a":0.018886},{"bsns_year":2018,"fs_div":"CFS","reprt_code":"11011","revenue":41425211029.0,"op_income":-9636961892.0,"net_income":-17026824667.0,"total_assets":148470846950.0,"total_liab":125560732307.0,"total_equity":22910114643.0,"per":null,"pbr":1.6768,"roe":-0.743201,"roic":-0.064908,"ev_ebit":null,"op_margin":-0.232635,"gp_a":0.048317},{"bsns_year":2019,"fs_div":"CFS","reprt_code":"11011","revenue":84340033510.0,"op_income":5348973307.0,"net_income":9251211968.0,"total_assets":138272304936.0,"total_liab":105526261155.0,"total_equity":32746043781.0,"per":4.1924,"pbr":1.1844,"roe":0.282514,"roic":0.038684,"ev_ebit":7.250903,"op_margin":0.063422,"gp_a":0.112408},{"bsns_year":2020,"fs_div":"CFS","reprt_code":"11011","revenue":21430920484.0,"op_income":-8229915505.0,"net_income":-5679930896.0,"total_assets":148381204902.0,"total_liab":119566802311.0,"total_equity":28814402591.0,"per":null,"pbr":0.6997,"roe":-0.197121,"roic":-0.055465,"ev_ebit":null,"op_margin":-0.384021,"gp_a":0.025866},{"bsns_year":2021,"fs_div":"CFS","reprt_code":"11011","revenue":19927877859.0,"op_income":-11569032637.0,"net_income":-14564982275.0,"total_assets":205116392149.0,"total_liab":165907921007.0,"total_equity":39208471142.0,"per":null,"pbr":0.7482,"roe":-0.371475,"roic":-0.056402,"ev_ebit":null,"op_margin":-0.580545,"gp_a":0.004898},{"bsns_year":2022,"fs_div":"CFS","reprt_code":"11011","revenue":103479533792.0,"op_income":-2429370395.0,"net_income":-2857939588.0,"total_assets":293658961770.0,"total_liab":257283701586.0,"total_equity":36375260184.0,"per":null,"pbr":0.5041,"roe":-0.078568,"roic":-0.008273,"ev_ebit":null,"op_margin":-0.023477,"gp_a":0.051315},{"bsns_year":2023,"fs_div":"CFS","reprt_code":"11011","revenue":179411227278.0,"op_income":4402139918.0,"net_income":-3768463583.0,"total_assets":294765567665.0,"total_liab":262208274597.0,"total_equity":32557293068.0,"per":null,"pbr":0.581,"roe":-0.115749,"roic":0.014934,"ev_ebit":4.297047,"op_margin":0.024537,"gp_a":0.082899},{"bsns_year":2024,"fs_div":"CFS","reprt_code":"11011","revenue":157635399233.0,"op_income":2921575940.0,"net_income":4522529746.0,"total_assets":311672452190.0,"total_liab":272225371109.0,"total_equity":39447081081.0,"per":3.5978,"pbr":0.4125,"roe":0.114648,"roic":0.009374,"ev_ebit":5.569302,"op_margin":0.018534,"gp_a":0.062264},{"bsns_year":2025,"fs_div":"CFS","reprt_code":"11011","revenue":27787097614.0,"op_income":-4267410006.0,"net_income":-25587129332.0,"total_assets":302089443402.0,"total_liab":287980118906.0,"total_equity":14109324496.0,"per":null,"pbr":1.1627,"roe":-1.813491,"roic":-0.014126,"ev_ebit":null,"op_margin":-0.153575,"gp_a":0.01886},{"bsns_year":2026,"fs_div":"CFS","reprt_code":"11013","revenue":45916414321.0,"op_income":6003584834.0,"net_income":5378548873.0,"total_assets":264406293277.0,"total_liab":244482356939.0,"total_equity":19923936338.0,"per":1.0183,"pbr":0.2749,"roe":0.269954,"roic":0.022706,"ev_ebit":0.912313,"op_margin":0.13075,"gp_a":0.042818}],"prices":[{"ym":"201501","close":137.0},{"ym":"201502","close":126.0},{"ym":"201503","close":150.0},{"ym":"201504","close":157.0},{"ym":"201505","close":147.0},{"ym":"201506","close":141.0},{"ym":"201507","close":288.0},{"ym":"201508","close":229.0},{"ym":"201509","close":292.0},{"ym":"201510","close":325.0},{"ym":"201511","close":254.0},{"ym":"201512","close":219.0},{"ym":"201601","close":231.0},{"ym":"201602","close":252.0},{"ym":"201603","close":256.0},{"ym":"201604","close":233.0},{"ym":"201605","close":210.0},{"ym":"201606","close":310.0},{"ym":"201607","close":296.0},{"ym":"201608","close":266.0},{"ym":"201609","close":250.0},{"ym":"201610","close":211.0},{"ym":"201611","close":204.0},{"ym":"201612","close":183.0},{"ym":"201701","close":258.0},{"ym":"201702","close":450.0},{"ym":"201703","close":272.0},{"ym":"201704","close":272.0},{"ym":"201705","close":274.0},{"ym":"201706","close":239.0},{"ym":"201707","close":187.0},{"ym":"201708","close":216.0},{"ym":"201709","close":158.0},{"ym":"201710","close":154.0},{"ym":"201711","close":170.0},{"ym":"201712","close":170.0},{"ym":"201801","close":191.0},{"ym":"201802","close":170.0},{"ym":"201803","close":140.0},{"ym":"201804","close":160.0},{"ym":"201805","close":150.0},{"ym":"201806","close":133.0},{"ym":"201807","close":131.0},{"ym":"201808","close":123.0},{"ym":"201809","close":115.0},{"ym":"201810","close":107.0},{"ym":"201811","close":118.0},{"ym":"201812","close":108.0},{"ym":"201901","close":108.0},{"ym":"201902","close":102.0},{"ym":"201903","close":99.0},{"ym":"201904","close":99.0},{"ym":"201905","close":99.0},{"ym":"201906","close":99.0},{"ym":"201907","close":99.0},{"ym":"201908","close":495.0},{"ym":"201909","close":495.0},{"ym":"201910","close":495.0},{"ym":"201911","close":495.0},{"ym":"201912","close":495.0},{"ym":"202001","close":495.0},{"ym":"202002","close":495.0},{"ym":"202003","close":495.0},{"ym":"202004","close":495.0},{"ym":"202005","close":495.0},{"ym":"202006","close":495.0},{"ym":"202007","close":495.0},{"ym":"202008","close":495.0},{"ym":"202009","close":495.0},{"ym":"202010","close":1190.0},{"ym":"202011","close":1380.0},{"ym":"202012","close":1220.0},{"ym":"202101","close":1150.0},{"ym":"202102","close":911.0},{"ym":"202103","close":1120.0},{"ym":"202104","close":2030.0},{"ym":"202105","close":1390.0},{"ym":"202106","close":1455.0},{"ym":"202107","close":2015.0},{"ym":"202108","close":2340.0},{"ym":"202109","close":1875.0},{"ym":"202110","close":1560.0},{"ym":"202111","close":1165.0},{"ym":"202112","close":1260.0},{"ym":"202201","close":1125.0},{"ym":"202202","close":1005.0},{"ym":"202203","close":1270.0},{"ym":"202204","close":1265.0},{"ym":"202205","close":1330.0},{"ym":"202206","close":1005.0},{"ym":"202207","close":1020.0},{"ym":"202208","close":945.0},{"ym":"202209","close":749.0},{"ym":"202210","close":770.0},{"ym":"202211","close":848.0},{"ym":"202212","close":738.0},{"ym":"202301","close":770.0},{"ym":"202302","close":767.0},{"ym":"202303","close":585.0},{"ym":"202304","close":1144.0},{"ym":"202305","close":890.0},{"ym":"202306","close":768.0},{"ym":"202307","close":774.0},{"ym":"202308","close":718.0},{"ym":"202309","close":705.0},{"ym":"202310","close":666.0},{"ym":"202311","close":682.0},{"ym":"202312","close":708.0},{"ym":"202401","close":647.0},{"ym":"202402","close":640.0},{"ym":"202403","close":682.0},{"ym":"202404","close":555.0},{"ym":"202405","close":534.0},{"ym":"202406","close":508.0},{"ym":"202407","close":484.0},{"ym":"202408","close":473.0},{"ym":"202409","close":465.0},{"ym":"202410","close":468.0},{"ym":"202411","close":406.0},{"ym":"202412","close":609.0},{"ym":"202501","close":459.0},{"ym":"202502","close":450.0},{"ym":"202503","close":1063.0},{"ym":"202504","close":779.0},{"ym":"202505","close":708.0},{"ym":"202506","close":620.0},{"ym":"202507","close":537.0},{"ym":"202508","close":672.0},{"ym":"202509","close":714.0},{"ym":"202510","close":755.0},{"ym":"202511","close":559.0},{"ym":"202512","close":614.0},{"ym":"202601","close":362.0},{"ym":"202602","close":312.0},{"ym":"202603","close":205.0},{"ym":"202604","close":205.0},{"ym":"202605","close":205.0},{"ym":"202606","close":205.0}]}