{"stock_code":"223310","name":"이에스브이","market":"KOSDAQ","sector":null,"years":[{"bsns_year":2015,"fs_div":"CFS","reprt_code":"11011","revenue":59356193658.0,"op_income":6554875005.0,"net_income":5078206021.0,"total_assets":34769729620.0,"total_liab":6622230315.0,"total_equity":28147499305.0,"per":14.926,"pbr":2.6929,"roe":0.180414,"roic":0.188522,"ev_ebit":11.5635,"op_margin":0.110433,"gp_a":0.271573},{"bsns_year":2016,"fs_div":"OFS","reprt_code":"11011","revenue":32856767945.0,"op_income":-3529470831.0,"net_income":-2248496771.0,"total_assets":31830799627.0,"total_liab":4922834194.0,"total_equity":26907965433.0,"per":null,"pbr":2.5985,"roe":-0.083562,"roic":-0.110882,"ev_ebit":null,"op_margin":-0.10742,"gp_a":0.089479},{"bsns_year":2017,"fs_div":"CFS","reprt_code":"11011","revenue":15183137605.0,"op_income":-15561877947.0,"net_income":-27635431323.0,"total_assets":55926340744.0,"total_liab":40725273197.0,"total_equity":15201067547.0,"per":null,"pbr":5.5919,"roe":-1.817993,"roic":-0.278257,"ev_ebit":null,"op_margin":-1.024945,"gp_a":-0.01823},{"bsns_year":2018,"fs_div":"CFS","reprt_code":"11011","revenue":16095117219.0,"op_income":-12477209002.0,"net_income":-25253936582.0,"total_assets":66456582238.0,"total_liab":35954117807.0,"total_equity":30502464431.0,"per":null,"pbr":3.2011,"roe":-0.827931,"roic":-0.18775,"ev_ebit":null,"op_margin":-0.775217,"gp_a":0.042935},{"bsns_year":2019,"fs_div":"CFS","reprt_code":"11011","revenue":9051493564.0,"op_income":73015626.0,"net_income":-2899961780.0,"total_assets":40535220661.0,"total_liab":8929667297.0,"total_equity":31605553364.0,"per":null,"pbr":0.6772,"roe":-0.091755,"roic":0.001801,"ev_ebit":293.142018,"op_margin":0.008067,"gp_a":0.054595},{"bsns_year":2020,"fs_div":"CFS","reprt_code":"11011","revenue":10174799516.0,"op_income":-4705423349.0,"net_income":-9759845705.0,"total_assets":31816541865.0,"total_liab":6503217973.0,"total_equity":25313323892.0,"per":null,"pbr":1.4947,"roe":-0.385562,"roic":-0.147892,"ev_ebit":null,"op_margin":-0.462459,"gp_a":0.022262},{"bsns_year":2021,"fs_div":"CFS","reprt_code":"11011","revenue":16677098599.0,"op_income":-4439010761.0,"net_income":-8361520141.0,"total_assets":23337207688.0,"total_liab":3417037349.0,"total_equity":19920170339.0,"per":null,"pbr":2.2222,"roe":-0.419751,"roic":-0.190212,"ev_ebit":null,"op_margin":-0.266174,"gp_a":0.076728},{"bsns_year":2022,"fs_div":"CFS","reprt_code":"11013","revenue":4564470878.0,"op_income":88567385.0,"net_income":486194942.0,"total_assets":23841270806.0,"total_liab":3434562718.0,"total_equity":20406708088.0,"per":107.4154,"pbr":2.5592,"roe":0.023825,"roic":0.003715,"ev_ebit":589.662117,"op_margin":0.019404,"gp_a":0.058434},{"bsns_year":2023,"fs_div":"OFS","reprt_code":"11011","revenue":27520272873.0,"op_income":293842758.0,"net_income":-1317336656.0,"total_assets":25658157819.0,"total_liab":3241272622.0,"total_equity":22416885197.0,"per":null,"pbr":1.1761,"roe":-0.058765,"roic":0.011452,"ev_ebit":89.721802,"op_margin":0.010677,"gp_a":0.318643},{"bsns_year":2024,"fs_div":"CFS","reprt_code":"11011","revenue":21744455014.0,"op_income":-3220882649.0,"net_income":-10367381699.0,"total_assets":35281055388.0,"total_liab":14163177911.0,"total_equity":21117877477.0,"per":null,"pbr":2.8065,"roe":-0.490929,"roic":-0.091292,"ev_ebit":null,"op_margin":-0.148124,"gp_a":0.199086},{"bsns_year":2025,"fs_div":"CFS","reprt_code":"11011","revenue":18896124016.0,"op_income":-7477162029.0,"net_income":-31524469694.0,"total_assets":69196205413.0,"total_liab":51931600103.0,"total_equity":17264605310.0,"per":null,"pbr":3.497,"roe":-1.825959,"roic":-0.108057,"ev_ebit":null,"op_margin":-0.395698,"gp_a":0.105103},{"bsns_year":2026,"fs_div":"CFS","reprt_code":"11013","revenue":6241219715.0,"op_income":-1436729719.0,"net_income":-10362302943.0,"total_assets":61018766999.0,"total_liab":54177781406.0,"total_equity":6840985593.0,"per":null,"pbr":2.9595,"roe":-1.514738,"roic":-0.023546,"ev_ebit":null,"op_margin":-0.2302,"gp_a":0.028331}],"prices":[{"ym":"201512","close":14500.0},{"ym":"201601","close":16500.0},{"ym":"201602","close":13700.0},{"ym":"201603","close":17600.0},{"ym":"201604","close":14900.0},{"ym":"201605","close":13150.0},{"ym":"201606","close":12550.0},{"ym":"201607","close":12800.0},{"ym":"201608","close":11850.0},{"ym":"201609","close":11950.0},{"ym":"201610","close":11500.0},{"ym":"201611","close":9020.0},{"ym":"201612","close":10550.0},{"ym":"201701","close":13200.0},{"ym":"201702","close":15500.0},{"ym":"201703","close":14700.0},{"ym":"201704","close":14000.0},{"ym":"201705","close":1865.0},{"ym":"201706","close":1440.0},{"ym":"201707","close":1270.0},{"ym":"201708","close":1205.0},{"ym":"201709","close":1020.0},{"ym":"201710","close":1350.0},{"ym":"201711","close":1295.0},{"ym":"201712","close":1070.0},{"ym":"201801","close":1290.0},{"ym":"201802","close":1095.0},{"ym":"201803","close":941.0},{"ym":"201804","close":1210.0},{"ym":"201805","close":1015.0},{"ym":"201806","close":1040.0},{"ym":"201807","close":1000.0},{"ym":"201808","close":1100.0},{"ym":"201809","close":1000.0},{"ym":"201810","close":867.0},{"ym":"201811","close":874.0},{"ym":"201812","close":864.0},{"ym":"201901","close":863.0},{"ym":"201902","close":759.0},{"ym":"201903","close":382.0},{"ym":"201904","close":357.0},{"ym":"201905","close":307.0},{"ym":"201906","close":285.0},{"ym":"201907","close":232.0},{"ym":"201908","close":206.0},{"ym":"201909","close":169.0},{"ym":"201910","close":171.0},{"ym":"201911","close":194.0},{"ym":"201912","close":174.0},{"ym":"202001","close":126.0},{"ym":"202002","close":145.0},{"ym":"202003","close":234.0},{"ym":"202004","close":166.0},{"ym":"202005","close":166.0},{"ym":"202006","close":166.0},{"ym":"202007","close":3320.0},{"ym":"202008","close":3320.0},{"ym":"202009","close":3320.0},{"ym":"202010","close":3320.0},{"ym":"202011","close":3320.0},{"ym":"202012","close":3320.0},{"ym":"202101","close":3320.0},{"ym":"202102","close":3320.0},{"ym":"202103","close":3320.0},{"ym":"202104","close":3320.0},{"ym":"202105","close":3320.0},{"ym":"202106","close":3320.0},{"ym":"202107","close":3320.0},{"ym":"202108","close":3320.0},{"ym":"202109","close":3320.0},{"ym":"202110","close":3320.0},{"ym":"202111","close":3320.0},{"ym":"202112","close":3320.0},{"ym":"202201","close":3320.0},{"ym":"202202","close":3320.0},{"ym":"202203","close":3320.0},{"ym":"202204","close":3320.0},{"ym":"202205","close":3320.0},{"ym":"202206","close":3320.0},{"ym":"202207","close":3320.0},{"ym":"202208","close":3320.0},{"ym":"202209","close":3320.0},{"ym":"202210","close":3320.0},{"ym":"202211","close":3320.0},{"ym":"202212","close":3320.0},{"ym":"202301","close":3320.0},{"ym":"202302","close":3320.0},{"ym":"202303","close":3320.0},{"ym":"202304","close":3320.0},{"ym":"202305","close":3320.0},{"ym":"202306","close":2250.0},{"ym":"202307","close":1888.0},{"ym":"202308","close":1845.0},{"ym":"202309","close":1651.0},{"ym":"202310","close":1529.0},{"ym":"202311","close":1590.0},{"ym":"202312","close":1676.0},{"ym":"202401","close":1603.0},{"ym":"202402","close":1476.0},{"ym":"202403","close":1449.0},{"ym":"202404","close":2080.0},{"ym":"202405","close":3090.0},{"ym":"202406","close":3055.0},{"ym":"202407","close":3525.0},{"ym":"202408","close":3050.0},{"ym":"202409","close":2470.0},{"ym":"202410","close":2210.0},{"ym":"202411","close":2030.0},{"ym":"202412","close":2595.0},{"ym":"202501","close":2740.0},{"ym":"202502","close":2685.0},{"ym":"202503","close":2370.0},{"ym":"202504","close":2795.0},{"ym":"202505","close":2920.0},{"ym":"202506","close":5950.0},{"ym":"202507","close":4175.0},{"ym":"202508","close":3165.0},{"ym":"202509","close":3165.0},{"ym":"202510","close":2880.0},{"ym":"202511","close":2165.0},{"ym":"202512","close":2320.0},{"ym":"202601","close":2035.0},{"ym":"202602","close":1604.0},{"ym":"202603","close":1482.0},{"ym":"202604","close":2275.0},{"ym":"202605","close":7000.0},{"ym":"202606","close":3890.0}]}